mymathlibrary/__init__.py
mymathlibrary/geometry.py
mymathlibrary/math.py
mymathlibrary/matrix.py
mymathlibrary-1.0.0.dist-info/METADATA
mymathlibrary-1.0.0.dist-info/WHEEL
mymathlibrary-1.0.0.dist-info/top_level.txt
mymathlibrary-1.0.0.dist-info/RECORD
